mtmbbox/__init__.py
mtmbbox/beautybox.py
mtmbbox/beautybox.pyi
mtmbbox/constants.py
mtmbbox/exceptions.py
mtmbbox/request.py
mtmbbox/utils.py
mtmbbox-3.2.3.dist-info/licenses/LICENSE
mtmbbox-3.2.3.dist-info/METADATA
mtmbbox-3.2.3.dist-info/WHEEL
mtmbbox-3.2.3.dist-info/top_level.txt
mtmbbox-3.2.3.dist-info/RECORD
