Metadata-Version: 2.4
Name: mtmbbox
Version: 3.2.3
Summary: Description
License: MIT License
Classifier: Development Status :: 3 - Alpha
Classifier: Programming Language :: Python :: 3.2
Classifier: Intended Audience :: Developers
Classifier: License :: OSI Approved :: MIT License
Classifier: Operating System :: MacOS
Classifier: Operating System :: POSIX :: Linux
Classifier: Operating System :: Microsoft :: Windows
Requires-Python: >=3.8
License-File: LICENSE
Requires-Dist: fastapi
Requires-Dist: pydantic
Requires-Dist: starlette
Requires-Dist: uvicorn
Requires-Dist: requests
Requires-Dist: pandas
Requires-Dist: redis
Requires-Dist: telebot
Requires-Dist: mtmqujing
Requires-Dist: mtmtool
Requires-Dist: aiohttp
Requires-Dist: httpx
Dynamic: license-file
